dkrutil/__init__.py
dkrutil/__main__.py
dkrutil/cli/__init__.py
dkrutil/cli/container.py
dkrutil/cli/dkrutil.py
dkrutil/cli/image.py
dkrutil/cli/rich.py
dkrutil/cli/secret.py
dkrutil/cli/volume.py
dkrutil/core/__init__.py
dkrutil/core/docker_client.py
dkrutil-1.0.3.dist-info/METADATA
dkrutil-1.0.3.dist-info/WHEEL
dkrutil-1.0.3.dist-info/entry_points.txt
dkrutil-1.0.3.dist-info/RECORD
