Metadata-Version: 2.3
Name: dkrutil
Version: 1.0.3
Summary: Dkrutil is a command-line tool that provides utility functions for managing Docker containers, volumes, and images. It simplifies common tasks like listing running containers, backing up and restoring volumes, and retrieving Docker image tags from Docker Hub.
Author: emerick-biron
Requires-Python: >=3.12,<4.0
Classifier: Programming Language :: Python :: 3
Classifier: Programming Language :: Python :: 3.12
Classifier: Programming Language :: Python :: 3.13
Requires-Dist: docker (>=7.1.0,<8.0.0)
Requires-Dist: requests (>=2.32.3,<3.0.0)
Requires-Dist: rich (>=14.0.0,<15.0.0)
Requires-Dist: rich-click (>=1.8.8,<2.0.0)
Project-URL: Homepage, https://github.com/emerick-biron/dkrutil
Project-URL: Repository, https://github.com/emerick-biron/dkrutil.git
